Marceau
