Metadata-Version: 2.1
Name: Marceau
Version: 0.46
Summary: Panjer's Algorithm in Python
Home-page: https://github.com/despervita/Marceau
Author: Rayane Vigneron
Author-email: rayanevigneron@yahoo.fr
License: MIT
Download-URL: https://github.com/despervita/Marceau/archive/v_046.tar.gz
Keywords: Panjer,Python
Platform: UNKNOWN
Classifier: Development Status :: 3 - Alpha
Classifier: Intended Audience :: Developers
Classifier: Topic :: Software Development :: Build Tools
Classifier: License :: OSI Approved :: MIT License
Classifier: Programming Language :: Python :: 3.9
